{
    "scraped_date": "2017-12-22",
    "categories": [
        {
            "category": "2011 and Later",
            "sub_category": [
                {
                    "category": "2.5HP",
                    "sub_category": [
                        {
                            "category": "DF2.5",
                            "sub_category": [
                                {
                                    "products": [
                                        {
                                            "image": "//cdn.boats.net/product/oem/bn/0/2/6/0264eb06af070521418673499484e66a.jpg",
                                            "diagram_number": "1",
                                            "product": "CARBURETOR",
                                            "manufacturer": "Suzuki Marine",
                                            "list_price": "$142.20",
                                            "product_url": "/parts/detail/suzuki/S-13200-97J50.html",
                                            "part_number": "13200-97J50",
                                            "your_price": "$115.30"
                                        },
                                        {
                                            "image": "//cdn.boats.net/label/S-13236-97J30.gif",
                                            "diagram_number": "2",
                                            "product": "NOZZLE, MAIN",
                                            "manufacturer": "Suzuki Marine",
                                            "list_price": "$18.92",
                                            "product_url": "/parts/detail/suzuki/S-13236-97J30.html",
                                            "part_number": "13236-97J30",
                                            "your_price": "$15.34"
                                        },
                                        {
                                            "image": "//cdn.boats.net/label/S-09491-60014.gif",
                                            "diagram_number": "3",
                                            "product": "JET, MAIN (60)",
                                            "manufacturer": "Suzuki Marine",
                                            "list_price": "$9.98",
                                            "product_url": "/parts/detail/suzuki/S-09491-60014.html",
                                            "part_number": "09491-60014",
                                            "your_price": "$8.09"
                                        },
                                        {
                                            "image": "//cdn.boats.net/label/S-09491-62009.gif",
                                            "diagram_number": "3",
                                            "product": "JET, MAIN (62)",
                                            "recomended": {
                                                "image": "//cdn.boats.net/label/S-09491-60014.gif",
                                                "diagram_number": "3",
                                                "product": "JET, MAIN (60)",
                                                "manufacturer": "Suzuki Marine",
                                                "list_price": "$9.98",
                                                "product_url": "/parts/detail/suzuki/S-09491-60014.html",
                                                "part_number": "09491-60014",
                                                "your_price": "$8.09"
                                            },
                                            "list_price": "$9.88",
                                            "product_url": "/parts/detail/suzuki/S-09491-62009.html",
                                            "part_number": "09491-62009",
                                            "manufacturer": "Suzuki Marine"
                                        },
                                        {
                                            "image": "//cdn.boats.net/product/oem/bn/2/7/d/27d395a7ccb3fccb691accc97ca73216.jpg",
                                            "diagram_number": "3",
                                            "product": "JET, MAIN (64)",
                                            "recomended": {
                                                "image": "//cdn.boats.net/label/S-09491-62009.gif",
                                                "diagram_number": "3",
                                                "product": "JET, MAIN (62)",
                                                "recomended": {
                                                    "image": "//cdn.boats.net/label/S-09491-60014.gif",
                                                    "diagram_number": "3",
                                                    "product": "JET, MAIN (60)",
                                                    "manufacturer": "Suzuki Marine",
                                                    "list_price": "$9.98",
                                                    "product_url": "/parts/detail/suzuki/S-09491-60014.html",
                                                    "part_number": "09491-60014",
                                                    "your_price": "$8.09"
                                                },
                                                "list_price": "$9.88",
                                                "product_url": "/parts/detail/suzuki/S-09491-62009.html",
                                                "part_number": "09491-62009",
                                                "manufacturer": "Suzuki Marine"
                                            },
                                            "list_price": "$9.88",
                                            "product_url": "/parts/detail/suzuki/S-09491-64003.html",
                                            "part_number": "09491-64003",
                                            "manufacturer": "Suzuki Marine"
                                        },
                                        {
                                            "image": "//cdn.boats.net/label/S-13371-97J00.gif",
                                            "diagram_number": "4",
                                            "product": "VALVE, NEEDLE",
                                            "manufacturer": "Suzuki Marine",
                                            "list_price": "$18.92",
                                            "product_url": "/parts/detail/suzuki/S-13371-97J00.html",
                                            "part_number": "13371-97J00",
                                            "your_price": "$15.34"
                                        },
                                        {
                                            "image": "//cdn.boats.net/label/S-13250-97J00.gif",
                                            "diagram_number": "5",
                                            "product": "FLOAT",
                                            "manufacturer": "Suzuki Marine",
                                            "list_price": "$24.43",
                                            "product_url": "/parts/detail/suzuki/S-13250-97J00.html",
                                            "part_number": "13250-97J00",
                                            "your_price": "$19.81"
                                        },
                                        {
                                            "image": "//cdn.boats.net/product/oem/bn/4/d/1/4d17d2a47ce070f93476caf2e57b389d.jpg",
                                            "diagram_number": "6",
                                            "product": "PIN, FLOAT",
                                            "manufacturer": "Suzuki Marine",
                                            "list_price": "$2.80",
                                            "product_url": "/parts/detail/suzuki/S-13254-97J00.html",
                                            "part_number": "13254-97J00",
                                            "your_price": "$2.27"
                                        },
                                        {
                                            "image": "//cdn.boats.net/product/oem/bn/3/b/d/3bd213db7c50be47b4933864b0ab96cb.jpg",
                                            "diagram_number": "7",
                                            "product": "SPRING",
                                            "manufacturer": "Suzuki Marine",
                                            "list_price": "$2.49",
                                            "product_url": "/parts/detail/suzuki/S-13268-97J30.html",
                                            "part_number": "13268-97J30",
                                            "your_price": "$2.01"
                                        },
                                        {
                                            "image": "//cdn.boats.net/product/oem/bn/5/2/b/52b518c5cbab44168d9979dbe5640c3f.jpg",
                                            "diagram_number": "8",
                                            "product": "GASKET",
                                            "manufacturer": "Suzuki Marine",
                                            "list_price": "$5.47",
                                            "product_url": "/parts/detail/suzuki/S-13251-97J00.html",
                                            "part_number": "13251-97J00",
                                            "your_price": "$4.43"
                                        },
                                        {
                                            "image": "//cdn.boats.net/label/S-13245-97J00.gif",
                                            "diagram_number": "9",
                                            "product": "CHAMBER, FLOAT",
                                            "list_price": "$44.83",
                                            "product_url": "/parts/detail/suzuki/S-13245-97J00.html",
                                            "part_number": "13245-97J00",
                                            "manufacturer": "Suzuki Marine"
                                        },
                                        {
                                            "image": "//cdn.boats.net/label/S-13249-97J00.gif",
                                            "diagram_number": "10",
                                            "product": "GASKET",
                                            "manufacturer": "Suzuki Marine",
                                            "list_price": "$2.08",
                                            "product_url": "/parts/detail/suzuki/S-13249-97J00.html",
                                            "part_number": "13249-97J00",
                                            "your_price": "$1.69"
                                        },
                                        {
                                            "image": "//cdn.boats.net/label/S-13247-97J00.gif",
                                            "diagram_number": "11",
                                            "product": "SCREW",
                                            "list_price": "$3.12",
                                            "product_url": "/parts/detail/suzuki/S-13247-97J00.html",
                                            "part_number": "13247-97J00",
                                            "manufacturer": "Suzuki Marine"
                                        },
                                        {
                                            "image": "//cdn.boats.net/label/S-13268-97J10.gif",
                                            "diagram_number": "12",
                                            "product": "SPRING",
                                            "manufacturer": "Suzuki Marine",
                                            "list_price": "$3.30",
                                            "product_url": "/parts/detail/suzuki/S-13268-97J10.html",
                                            "part_number": "13268-97J10",
                                            "your_price": "$2.68"
                                        },
                                        {
                                            "image": "//cdn.boats.net/label/S-13616-97J00.gif",
                                            "diagram_number": "13",
                                            "product": "SCREW",
                                            "manufacturer": "Suzuki Marine",
                                            "list_price": "$17.02",
                                            "product_url": "/parts/detail/suzuki/S-13616-97J00.html",
                                            "part_number": "13616-97J00",
                                            "your_price": "$13.80"
                                        },
                                        {
                                            "image": "//cdn.boats.net/label/S-13267-97J00.gif",
                                            "diagram_number": "14",
                                            "product": "SCREW",
                                            "list_price": "$1.34",
                                            "product_url": "/parts/detail/suzuki/S-13267-97J00.html",
                                            "part_number": "13267-97J00",
                                            "manufacturer": "Suzuki Marine"
                                        },
                                        {
                                            "image": "//cdn.boats.net/label/S-09492-32011.gif",
                                            "diagram_number": "15",
                                            "product": "JET, PILOT (32)",
                                            "manufacturer": "Suzuki Marine",
                                            "list_price": "$12.12",
                                            "product_url": "/parts/detail/suzuki/S-09492-32011.html",
                                            "part_number": "09492-32011",
                                            "your_price": "$10.18"
                                        },
                                        {
                                            "image": "//cdn.boats.net/product/oem/bn/2/d/6/2d617ef71c0a3fb9a04c6386686dfbff.jpg",
                                            "diagram_number": "15",
                                            "product": "JET, PILOT (34)",
                                            "recomended": {
                                                "image": "//cdn.boats.net/label/S-09492-32011.gif",
                                                "diagram_number": "15",
                                                "product": "JET, PILOT (32)",
                                                "manufacturer": "Suzuki Marine",
                                                "list_price": "$12.12",
                                                "product_url": "/parts/detail/suzuki/S-09492-32011.html",
                                                "part_number": "09492-32011",
                                                "your_price": "$10.18"
                                            },
                                            "manufacturer": "Suzuki Marine",
                                            "list_price": "$12.12",
                                            "product_url": "/parts/detail/suzuki/S-09492-34004.html",
                                            "part_number": "09492-34004",
                                            "your_price": "$10.18"
                                        },
                                        {
                                            "image": "//cdn.boats.net/label/S-09492-36L01.gif",
                                            "diagram_number": "15",
                                            "product": "JET, PILOT (36)",
                                            "recomended": {
                                                "image": "//cdn.boats.net/product/oem/bn/2/d/6/2d617ef71c0a3fb9a04c6386686dfbff.jpg",
                                                "diagram_number": "15",
                                                "product": "JET, PILOT (34)",
                                                "recomended": {
                                                    "image": "//cdn.boats.net/label/S-09492-32011.gif",
                                                    "diagram_number": "15",
                                                    "product": "JET, PILOT (32)",
                                                    "manufacturer": "Suzuki Marine",
                                                    "list_price": "$12.12",
                                                    "product_url": "/parts/detail/suzuki/S-09492-32011.html",
                                                    "part_number": "09492-32011",
                                                    "your_price": "$10.18"
                                                },
                                                "manufacturer": "Suzuki Marine",
                                                "list_price": "$12.12",
                                                "product_url": "/parts/detail/suzuki/S-09492-34004.html",
                                                "part_number": "09492-34004",
                                                "your_price": "$10.18"
                                            },
                                            "manufacturer": "Suzuki Marine",
                                            "list_price": "$9.98",
                                            "product_url": "/parts/detail/suzuki/S-09492-36L01.html",
                                            "part_number": "09492-36L01",
                                            "your_price": "$8.09"
                                        },
                                        {
                                            "image": "//cdn.boats.net/label/S-13267-97J10.gif",
                                            "diagram_number": "16",
                                            "product": "SCREW",
                                            "manufacturer": "Suzuki Marine",
                                            "list_price": "$4.07",
                                            "product_url": "/parts/detail/suzuki/S-13267-97J10.html",
                                            "part_number": "13267-97J10",
                                            "your_price": "$3.30"
                                        },
                                        {
                                            "image": "//cdn.boats.net/label/S-09493-27L01.gif",
                                            "diagram_number": "17",
                                            "product": "JET, PILOT AIR (135)",
                                            "manufacturer": "Suzuki Marine",
                                            "list_price": "$9.35",
                                            "product_url": "/parts/detail/suzuki/S-09493-27L01.html",
                                            "part_number": "09493-27L01",
                                            "your_price": "$7.58"
                                        },
                                        {
                                            "image": "//cdn.boats.net/label/S-09493-29004.gif",
                                            "diagram_number": "18",
                                            "product": "JET, PILOT AIR (145)",
                                            "list_price": "$9.53",
                                            "product_url": "/parts/detail/suzuki/S-09493-29004.html",
                                            "part_number": "09493-29004",
                                            "manufacturer": "Suzuki Marine"
                                        },
                                        {
                                            "image": "//cdn.boats.net/product/oem/bn/1/6/8/168cae5b9b00542a5563dee300040219.jpg",
                                            "diagram_number": "19",
                                            "product": "GASKET",
                                            "manufacturer": "Suzuki Marine",
                                            "list_price": "$9.57",
                                            "product_url": "/parts/detail/suzuki/S-13249-97J10.html",
                                            "part_number": "13249-97J10",
                                            "your_price": "$7.77"
                                        },
                                        {
                                            "image": "//cdn.boats.net/label/S-13248-97J00.gif",
                                            "diagram_number": "20",
                                            "product": "PLATE",
                                            "list_price": "$13.48",
                                            "product_url": "/parts/detail/suzuki/S-13248-97J00.html",
                                            "part_number": "13248-97J00",
                                            "manufacturer": "Suzuki Marine"
                                        },
                                        {
                                            "diagram_number": "21"
                                        }
                                    ],
                                    "category": "CARBURETOR (210001~)",
                                    "image": "//cdn.boats.net/diagram/suzuki/11/102/0005.png",
                                    "category_name": "component",
                                    "category_url": "/parts/search/Suzuki/Outboard/2011 and Later/DF2.5/CARBURETOR (210001~)/parts.html"
                                }
                            ],
                            "category_name": "model",
                            "category_url": "/parts/search/Suzuki/Outboard/2011 and Later/DF2.5/parts.html"
                        }
                    ],
                    "category_name": "horse power",
                    "category_url": null
                }
            ],
            "category_name": "years",
            "category_url": "/parts/search/Suzuki/Outboard/2011 and Later/parts.html"
        }
    ],
    "scraping_successful": true
}